diffpy/__init__.py
diffpy/srmise/__init__.py
diffpy/srmise/basefunction.py
diffpy/srmise/dataclusters.py
diffpy/srmise/modelcluster.py
diffpy/srmise/modelparts.py
diffpy/srmise/multimodelselection.py
diffpy/srmise/pdfdataset.py
diffpy/srmise/pdfpeakextraction.py
diffpy/srmise/peakextraction.py
diffpy/srmise/peakstability.py
diffpy/srmise/srmiseerrors.py
diffpy/srmise/srmiselog.py
diffpy/srmise/version.py
diffpy/srmise/applications/__init__.py
diffpy/srmise/applications/extract.py
diffpy/srmise/applications/plot.py
diffpy/srmise/baselines/__init__.py
diffpy/srmise/baselines/arbitrary.py
diffpy/srmise/baselines/base.py
diffpy/srmise/baselines/fromsequence.py
diffpy/srmise/baselines/nanospherical.py
diffpy/srmise/baselines/polynomial.py
diffpy/srmise/modelevaluators/__init__.py
diffpy/srmise/modelevaluators/aic.py
diffpy/srmise/modelevaluators/aicc.py
diffpy/srmise/modelevaluators/base.py
diffpy/srmise/peaks/__init__.py
diffpy/srmise/peaks/base.py
diffpy/srmise/peaks/gaussian.py
diffpy/srmise/peaks/gaussianoverr.py
diffpy/srmise/peaks/terminationripples.py
diffpy.srmise-0.7.0.dist-info/AUTHORS.rst
diffpy.srmise-0.7.0.dist-info/LICENSE.rst
diffpy.srmise-0.7.0.dist-info/LICENSE_PDFgui.rst
diffpy.srmise-0.7.0.dist-info/METADATA
diffpy.srmise-0.7.0.dist-info/WHEEL
diffpy.srmise-0.7.0.dist-info/entry_points.txt
diffpy.srmise-0.7.0.dist-info/top_level.txt
diffpy.srmise-0.7.0.dist-info/RECORD
