Metadata-Version: 2.1
Name: diffpy.srmise
Version: 0.7.0
Summary: Peak extraction and peak fitting tool for atomic pair distribution functions.
Author-email: "Simon J.L. Billinge group" <simon.billinge@gmail.com>, Luke Granlund <granlund@pa.msu.edu>
Maintainer-email: "Simon J.L. Billinge group" <simon.billinge@gmail.com>
Project-URL: Homepage, https://github.com/diffpy/diffpy.srmise/
Project-URL: Issues, https://github.com/diffpy/diffpy.srmise/issues/
Keywords: peak extraction fitting PDF AIC multimodeling
Classifier: Development Status :: 3 - Alpha
Classifier: Environment :: Console
Classifier: Intended Audience :: Developers
Classifier: Intended Audience :: Science/Research
Classifier: Intended Audience :: Education
Classifier: License :: OSI Approved :: BSD License
Classifier: Operating System :: MacOS :: MacOS X
Classifier: Operating System :: Microsoft :: Windows
Classifier: Operating System :: POSIX
Classifier: Operating System :: Unix
Classifier: Programming Language :: Python :: 3.11
Classifier: Programming Language :: Python :: 3.12
Classifier: Programming Language :: Python :: 3.13
Classifier: Topic :: Scientific/Engineering :: Physics
Classifier: Topic :: Scientific/Engineering :: Chemistry
Classifier: Topic :: Software Development :: Libraries
Requires-Python: <3.14,>=3.11
License-File: LICENSE.rst
License-File: LICENSE_PDFgui.rst
License-File: AUTHORS.rst
Requires-Dist: numpy
Requires-Dist: scipy
Requires-Dist: matplotlib
